lowball_rabbitmq_logging_handler/__init__.py
lowball_rabbitmq_logging_handler/lowball_rabbitmq_logging_handler.py
lowball_rabbitmq_logging_handler-1.0.0.dist-info/LICENSE
lowball_rabbitmq_logging_handler-1.0.0.dist-info/METADATA
lowball_rabbitmq_logging_handler-1.0.0.dist-info/WHEEL
lowball_rabbitmq_logging_handler-1.0.0.dist-info/top_level.txt
lowball_rabbitmq_logging_handler-1.0.0.dist-info/RECORD
